{
  "task_name": "08b-parallel-playwright-e2e-and-ui-acceptance-smoke",
  "task_path": "doc/02-application-implementation/08b-parallel-playwright-e2e-and-ui-acceptance-smoke",
  "wave": 8,
  "execution_mode": "parallel",
  "depends_on": [
    "06a-parallel-public-landing-directory-and-registration-pages",
    "06b-parallel-member-login-and-profile-pages",
    "06c-parallel-admin-dashboard-members-tags-schema-meetings-pages",
    "07a-parallel-tag-assignment-queue-resolve-workflow",
    "07b-parallel-schema-diff-alias-assignment-workflow",
    "07c-parallel-meeting-attendance-and-admin-audit-log-workflow"
  ],
  "blocks": [
    "09a-parallel-staging-deploy-smoke-and-forms-sync-validation",
    "09b-parallel-cron-triggers-monitoring-and-release-runbook"
  ],
  "created_at": "2026-04-26",
  "metadata": {
    "taskType": "spec_created",
    "docs_only": true,
    "scope": "application_implementation",
    "domain": "playwright_e2e_ui_acceptance"
  },
  "phases": [
    {
      "phase": 1,
      "name": "要件定義",
      "file": "phase-01.md",
      "status": "pending",
      "outputs": [
        "outputs/phase-01/main.md"
      ],
      "depends_on_phases": [],
      "user_approval_required": false
    },
    {
      "phase": 2,
      "name": "設計",
      "file": "phase-02.md",
      "status": "pending",
      "outputs": [
        "outputs/phase-02/main.md",
        "outputs/phase-02/e2e-architecture.mmd",
        "outputs/phase-02/scenario-matrix.md"
      ],
      "depends_on_phases": [
        1
      ],
      "user_approval_required": false
    },
    {
      "phase": 3,
      "name": "設計レビュー",
      "file": "phase-03.md",
      "status": "pending",
      "outputs": [
        "outputs/phase-03/main.md"
      ],
      "depends_on_phases": [
        2
      ],
      "user_approval_required": false
    },
    {
      "phase": 4,
      "name": "テスト戦略",
      "file": "phase-04.md",
      "status": "pending",
      "outputs": [
        "outputs/phase-04/main.md",
        "outputs/phase-04/verify-matrix.md"
      ],
      "depends_on_phases": [
        3
      ],
      "user_approval_required": false
    },
    {
      "phase": 5,
      "name": "実装ランブック",
      "file": "phase-05.md",
      "status": "pending",
      "outputs": [
        "outputs/phase-05/main.md",
        "outputs/phase-05/runbook.md",
        "outputs/phase-05/playwright-config.ts.placeholder",
        "outputs/phase-05/page-objects.md"
      ],
      "depends_on_phases": [
        4
      ],
      "user_approval_required": false
    },
    {
      "phase": 6,
      "name": "異常系検証",
      "file": "phase-06.md",
      "status": "pending",
      "outputs": [
        "outputs/phase-06/main.md"
      ],
      "depends_on_phases": [
        5
      ],
      "user_approval_required": false
    },
    {
      "phase": 7,
      "name": "AC マトリクス",
      "file": "phase-07.md",
      "status": "pending",
      "outputs": [
        "outputs/phase-07/main.md",
        "outputs/phase-07/ac-matrix.md"
      ],
      "depends_on_phases": [
        6
      ],
      "user_approval_required": false
    },
    {
      "phase": 8,
      "name": "DRY 化",
      "file": "phase-08.md",
      "status": "pending",
      "outputs": [
        "outputs/phase-08/main.md"
      ],
      "depends_on_phases": [
        7
      ],
      "user_approval_required": false
    },
    {
      "phase": 9,
      "name": "品質保証",
      "file": "phase-09.md",
      "status": "pending",
      "outputs": [
        "outputs/phase-09/main.md"
      ],
      "depends_on_phases": [
        8
      ],
      "user_approval_required": false
    },
    {
      "phase": 10,
      "name": "最終レビュー",
      "file": "phase-10.md",
      "status": "pending",
      "outputs": [
        "outputs/phase-10/main.md"
      ],
      "depends_on_phases": [
        9
      ],
      "user_approval_required": false
    },
    {
      "phase": 11,
      "name": "手動 smoke",
      "file": "phase-11.md",
      "status": "pending",
      "outputs": [
        "outputs/phase-11/main.md",
        "outputs/phase-11/evidence/",
        "outputs/phase-11/evidence/desktop/",
        "outputs/phase-11/evidence/mobile/",
        "outputs/phase-11/evidence/axe-report.json",
        "outputs/phase-11/evidence/playwright-report/",
        "outputs/phase-11/evidence/ci-workflow.yml"
      ],
      "depends_on_phases": [
        10
      ],
      "user_approval_required": false
    },
    {
      "phase": 12,
      "name": "ドキュメント更新",
      "file": "phase-12.md",
      "status": "pending",
      "outputs": [
        "outputs/phase-12/main.md",
        "outputs/phase-12/implementation-guide.md",
        "outputs/phase-12/system-spec-update-summary.md",
        "outputs/phase-12/documentation-changelog.md",
        "outputs/phase-12/unassigned-task-detection.md",
        "outputs/phase-12/skill-feedback-report.md",
        "outputs/phase-12/phase12-task-spec-compliance-check.md"
      ],
      "depends_on_phases": [
        11
      ],
      "user_approval_required": false
    },
    {
      "phase": 13,
      "name": "PR 作成",
      "file": "phase-13.md",
      "status": "pending",
      "outputs": [
        "outputs/phase-13/main.md",
        "outputs/phase-13/local-check-result.md",
        "outputs/phase-13/change-summary.md",
        "outputs/phase-13/pr-template.md"
      ],
      "depends_on_phases": [
        12
      ],
      "user_approval_required": true
    }
  ],
  "specs_referenced": [
    "doc/00-getting-started-manual/specs/09-ui-ux.md",
    "doc/00-getting-started-manual/specs/05-pages.md",
    "doc/00-getting-started-manual/specs/12-search-tags.md",
    "doc/00-getting-started-manual/specs/11-admin-management.md",
    "doc/00-getting-started-manual/specs/13-mvp-auth.md",
    "doc/00-getting-started-manual/specs/16-component-library.md",
    "doc/00-getting-started-manual/specs/00-overview.md"
  ],
  "endpoints": [],
  "d1_tables": [
    "members",
    "member_status",
    "member_attendance",
    "meeting_sessions",
    "tag_assignment_queue",
    "schema_diff_queue",
    "audit_log"
  ],
  "ui_routes": [
    "/",
    "/members",
    "/members/[id]",
    "/register",
    "/login",
    "/profile",
    "/admin",
    "/admin/members",
    "/admin/tags",
    "/admin/schema",
    "/admin/meetings"
  ],
  "secrets_introduced": [],
  "invariants_touched": [
    4,
    8,
    9,
    15
  ],
  "doc_references": [
    "doc/02-application-implementation/_design/phase-2-design.md#wave-8b",
    "doc/02-application-implementation/README.md"
  ]
}
